tuneparams/__init__.py
tuneparams/cli.py
tuneparams/script_modifier.py
tuneparams/utils.py
tuneparams-0.2.2.dist-info/METADATA
tuneparams-0.2.2.dist-info/WHEEL
tuneparams-0.2.2.dist-info/entry_points.txt
tuneparams-0.2.2.dist-info/top_level.txt
tuneparams-0.2.2.dist-info/RECORD
