Metadata-Version: 2.1
Name: tuneparams
Version: 0.2.2
Summary: A CLI tool to modify and execute Python scripts.
Home-page: https://github.com/Sudharshan281/tuneparams
Author: Sudharshan | Ashish | Risha Lab
Author-email: imsudharshan281@gmail.com
License: MIT
Platform: UNKNOWN
Requires-Dist: astor
